[
    {
        "key": "group_5b8aed125ea87",
        "title": "Realty Settings",
        "fields": [
            {
                "key": "field_5b8ad90a03a09",
                "label": "Base",
                "name": "",
                "type": "tab",
                "instructions": "",
                "required": 0,
                "conditional_logic": 0,
                "wrapper": {
                    "width": "",
                    "class": "",
                    "id": ""
                },
                "placement": "top",
                "endpoint": 0
            },
            {
                "key": "field_5b8ad99603a0b",
                "label": "Cost",
                "name": "cost",
                "type": "number",
                "instructions": "",
                "required": 1,
                "conditional_logic": 0,
                "wrapper": {
                    "width": "",
                    "class": "",
                    "id": ""
                },
                "default_value": "",
                "placeholder": "",
                "prepend": "$",
                "append": "",
                "min": "",
                "max": "",
                "step": ""
            },
            {
                "key": "field_5b8ad94c03a0a",
                "label": "Area",
                "name": "area",
                "type": "number",
                "instructions": "",
                "required": 1,
                "conditional_logic": 0,
                "wrapper": {
                    "width": "50",
                    "class": "",
                    "id": ""
                },
                "default_value": "",
                "placeholder": "",
                "prepend": "m²",
                "append": "",
                "min": "",
                "max": "",
                "step": ""
            },
            {
                "key": "field_5b8ad9bf03a0d",
                "label": "Living area",
                "name": "living_area",
                "type": "number",
                "instructions": "",
                "required": 0,
                "conditional_logic": 0,
                "wrapper": {
                    "width": "50",
                    "class": "",
                    "id": ""
                },
                "default_value": "",
                "placeholder": "",
                "prepend": "m²",
                "append": "",
                "min": "",
                "max": "",
                "step": ""
            },
            {
                "key": "field_5b8ada0003a0e",
                "label": "Floor",
                "name": "floor",
                "type": "number",
                "instructions": "",
                "required": 1,
                "conditional_logic": 0,
                "wrapper": {
                    "width": "",
                    "class": "",
                    "id": ""
                },
                "default_value": "",
                "placeholder": "",
                "prepend": "",
                "append": "",
                "min": "",
                "max": "",
                "step": ""
            },
            {
                "key": "field_5b8aef5795d37",
                "label": "City",
                "name": "city",
                "type": "post_object",
                "instructions": "",
                "required": 0,
                "conditional_logic": 0,
                "wrapper": {
                    "width": "",
                    "class": "",
                    "id": ""
                },
                "post_type": [
                    "city"
                ],
                "taxonomy": [],
                "allow_null": 0,
                "multiple": 0,
                "return_format": "object",
                "ui": 1
            },
            {
                "key": "field_5b8ad9ad03a0c",
                "label": "Address",
                "name": "address",
                "type": "text",
                "instructions": "",
                "required": 0,
                "conditional_logic": 0,
                "wrapper": {
                    "width": "",
                    "class": "",
                    "id": ""
                },
                "default_value": "",
                "placeholder": "",
                "prepend": "",
                "append": "",
                "formatting": "html",
                "maxlength": ""
            },
            {
                "key": "field_5b8ad81679f13",
                "label": "Gallery",
                "name": "",
                "type": "tab",
                "instructions": "",
                "required": 0,
                "conditional_logic": 0,
                "wrapper": {
                    "width": "",
                    "class": "",
                    "id": ""
                },
                "placement": "top",
                "endpoint": 0
            },
            {
                "key": "field_5b8ad1e956ae2",
                "label": "image_1",
                "name": "image_1",
                "type": "image",
                "instructions": "",
                "required": 0,
                "conditional_logic": 0,
                "wrapper": {
                    "width": "33",
                    "class": "",
                    "id": ""
                },
                "return_format": "id",
                "preview_size": "thumbnail",
                "library": "uploadedTo",
                "min_width": "",
                "min_height": "",
                "min_size": "",
                "max_width": "",
                "max_height": "",
                "max_size": "",
                "mime_types": ""
            },
            {
                "key": "field_5b8ad85479f14",
                "label": "image_2",
                "name": "image_2",
                "type": "image",
                "instructions": "",
                "required": 0,
                "conditional_logic": 0,
                "wrapper": {
                    "width": "33",
                    "class": "",
                    "id": ""
                },
                "return_format": "id",
                "preview_size": "thumbnail",
                "library": "uploadedTo",
                "min_width": "",
                "min_height": "",
                "min_size": "",
                "max_width": "",
                "max_height": "",
                "max_size": "",
                "mime_types": ""
            },
            {
                "key": "field_5b8ad85d79f15",
                "label": "image_3",
                "name": "image_3",
                "type": "image",
                "instructions": "",
                "required": 0,
                "conditional_logic": 0,
                "wrapper": {
                    "width": "33",
                    "class": "",
                    "id": ""
                },
                "return_format": "id",
                "preview_size": "thumbnail",
                "library": "uploadedTo",
                "min_width": "",
                "min_height": "",
                "min_size": "",
                "max_width": "",
                "max_height": "",
                "max_size": "",
                "mime_types": ""
            },
            {
                "key": "field_5b8ad86679f16",
                "label": "image_4",
                "name": "image_4",
                "type": "image",
                "instructions": "",
                "required": 0,
                "conditional_logic": 0,
                "wrapper": {
                    "width": "33",
                    "class": "",
                    "id": ""
                },
                "return_format": "id",
                "preview_size": "thumbnail",
                "library": "uploadedTo",
                "min_width": "",
                "min_height": "",
                "min_size": "",
                "max_width": "",
                "max_height": "",
                "max_size": "",
                "mime_types": ""
            },
            {
                "key": "field_5b8ad87279f17",
                "label": "image_5",
                "name": "image_5",
                "type": "image",
                "instructions": "",
                "required": 0,
                "conditional_logic": 0,
                "wrapper": {
                    "width": "33",
                    "class": "",
                    "id": ""
                },
                "return_format": "id",
                "preview_size": "thumbnail",
                "library": "uploadedTo",
                "min_width": "",
                "min_height": "",
                "min_size": "",
                "max_width": "",
                "max_height": "",
                "max_size": "",
                "mime_types": ""
            },
            {
                "key": "field_5b8ad87779f18",
                "label": "image_6",
                "name": "image_6",
                "type": "image",
                "instructions": "",
                "required": 0,
                "conditional_logic": 0,
                "wrapper": {
                    "width": "33",
                    "class": "",
                    "id": ""
                },
                "return_format": "id",
                "preview_size": "thumbnail",
                "library": "uploadedTo",
                "min_width": "",
                "min_height": "",
                "min_size": "",
                "max_width": "",
                "max_height": "",
                "max_size": "",
                "mime_types": ""
            }
        ],
        "location": [
            [
                {
                    "param": "post_type",
                    "operator": "==",
                    "value": "realty"
                }
            ]
        ],
        "menu_order": 0,
        "position": "normal",
        "style": "default",
        "label_placement": "top",
        "instruction_placement": "label",
        "hide_on_screen": "",
        "active": 1,
        "description": ""
    }
]